Workbook

Sheet Start Here
B1: Is our GenAI use case paying for itself?
B2: Answer eight plain questions for each use case (blue cells). The results below update instantly. No token math needed.
B3: Pre-filled with an illustrative worked example. Figures and methodology are illustrative; see the About tab for the full disclaimer. | H3: Version 1.0 · October 2026
H4: Open for use and adaptation with attribution (CC BY 4.0). See the About tab.
B5: Question | C5: Use case 1 | D5: Use case 2 | E5: Use case 3 | F5: Use case 4 | G5: Use case 5 | H5: Your guidance
B6: Use case name | C6: Customer service agent | D6: Contract clause extraction | E6: Invoice exception triage | F6: Internal knowledge assistant | H6: Any short label
B7: How many tasks does it handle a month? | C7: 60000 | D7: 3000 | E7: 25000 | F7: 150000 | H7: Tickets, contracts, invoices, queries
B8: How many minutes does a person take per task today? | C8: 9 | D8: 75 | E8: 8 | F8: 4 | H8: Average time without AI
B9: What does an hour of that person's time cost? ($) | C9: 32 | D9: 85 | E9: 28 | F9: 45 | H9: Fully loaded, salary plus overheads
B10: What share of tasks does the AI get right without rework? | C10: 0.78 | D10: 0.9 | E10: 0.85 | F10: 0.7 | H10: From a test set or QA sample. Failed tasks go back to a person
B11: How many minutes does a person spend checking each AI output? | C11: 1 | D11: 12 | E11: 1.5 | F11: 0 | H11: Review time on the tasks AI completes
B12: What does the AI cost per task? ($) | C12: 0.1184544 | D12: 0.6433875 | E12: 0.00230205 | F12: 0.027159 | H12: Ask your IT or AI team. Don't know? Leave blank and fill rows 13-14 instead
B13: If unknown: how big is each task? | H13: Light: short Q&A or classification · Medium: a multi-step conversation · Heavy: long documents
B14: If unknown: which model class? | H14: Economy, Standard or Premium
B15: Monthly platform and team cost carried by this use case ($) | C15: 24287 | D15: 6596 | E15: 197 | F15: 13921 | H15: Its share of gateway, monitoring, engineers. Total in example: $45,000
B16: How much of the time saved turns into real savings? | C16: 0.9 | D16: 0.8 | E16: 1 | F16: 0.4 | H16: 100% = fewer hires or contractors · 50% = partly redeployed · 25% = soft time savings
B18: Results
B19: Cost per task today, without AI | C19: =IF(C7="","",C8/60*C9) -> 4.8 | D19: =IF(D7="","",D8/60*D9) -> 106.25 | E19: =IF(E7="","",E8/60*E9) -> 3.7333333 | F19: =IF(F7="","",F8/60*F9) -> 3 | G19: =IF(G7="","",G8/60*G9)
B20: AI cost per task used | C20: =IF(C7="","",IF(C12<>"",C12,IFERROR(INDEX($C$37:$E$39,MATCH(C13,$A$37:$A$39,0),MATCH(C14,$C$36:$E$36,0)),0))) -> 0.1184544 | D20: =IF(D7="","",IF(D12<>"",D12,IFERROR(INDEX($C$37:$E$39,MATCH(D13,$A$37:$A$39,0),MATCH(D14,$C$36:$E$36,0)),0))) -> 0.6433875 | E20: =IF(E7="","",IF(E12<>"",E12,IFERROR(INDEX($C$37:$E$39,MATCH(E13,$A$37:$A$39,0),MATCH(E14,$C$36:$E$36,0)),0))) -> 0.00230205 | F20: =IF(F7="","",IF(F12<>"",F12,IFERROR(INDEX($C$37:$E$39,MATCH(F13,$A$37:$A$39,0),MATCH(F14,$C$36:$E$36,0)),0))) -> 0.027159 | G20: =IF(G7="","",IF(G12<>"",G12,IFERROR(INDEX($C$37:$E$39,MATCH(G13,$A$37:$A$39,0),MATCH(G14,$C$36:$E$36,0)),0)))
B21: AI cost per successful task, including platform | C21: =IF(C7="","",IF(C10=0,0,(C20+C15/C7)/C10)) -> 0.67081761 | D21: =IF(D7="","",IF(D10=0,0,(D20+D15/D7)/D10)) -> 3.157838 | E21: =IF(E7="","",IF(E10=0,0,(E20+E15/E7)/E10)) -> 0.011978882 | F21: =IF(F7="","",IF(F10=0,0,(F20+F15/F7)/F10)) -> 0.17137952 | G21: =IF(G7="","",IF(G10=0,0,(G20+G15/G7)/G10)) | H21: Portfolio total →
B22: Net value per month | C22: =IF(C7="","",((C19-(C11/60*C9+(1-C10)*C19))*C16-(C20+C15/C7))*C7) -> 141981.74 | D22: =IF(D7="","",((D19-(D11/60*D9+(1-D10)*D19))*D16-(D20+D15/D7))*D7) -> 180173.84 | E22: =IF(E7="","",((E19-(E11/60*E9+(1-E10)*E19))*E16-(E20+E15/E7))*E7) -> 61578.782 | F22: =IF(F7="","",((F19-(F11/60*F9+(1-F10)*F19))*F16-(F20+F15/F7))*F7) -> 108005.15 | G22: =IF(G7="","",((G19-(G11/60*G9+(1-G10)*G19))*G16-(G20+G15/G7))*G7) | H22: =SUM(C22:G22) -> 491739.51
B23: Net value per year | C23: =IF(C7="","",C22*12) -> 1703780.8 | D23: =IF(D7="","",D22*12) -> 2162086 | E23: =IF(E7="","",E22*12) -> 738945.39 | F23: =IF(F7="","",F22*12) -> 1296061.8 | G23: =IF(G7="","",G22*12) | H23: =SUM(C23:G23) -> 5900874.1
B24: Return per $1 of AI spend | C24: =IF(C7="","",IF((C20*C7+C15)=0,0,C22/(C20*C7+C15))) -> 4.5225375 | D24: =IF(D7="","",IF((D20*D7+D15)=0,0,D22/(D20*D7+D15))) -> 21.131879 | E24: =IF(E7="","",IF((E20*E7+E15)=0,0,E22/(E20*E7+E15))) -> 241.91114 | F24: =IF(F7="","",IF((F20*F7+F15)=0,0,F22/(F20*F7+F15))) -> 6.0020034 | G24: =IF(G7="","",IF((G20*G7+G15)=0,0,G22/(G20*G7+G15)))
B25: Lowest success rate at which it still pays | C25: =IF(C7="","",IF(OR(C19=0,C16=0),"n/a",IF(((C20+C15/C7)/C16+C11/60*C9)/C19>1,"Never pays",((C20+C15/C7)/C16+C11/60*C9)/C19))) -> 0.23223096 | D25: =IF(D7="","",IF(OR(D19=0,D16=0),"n/a",IF(((D20+D15/D7)/D16+D11/60*D9)/D19>1,"Never pays",((D20+D15/D7)/D16+D11/60*D9)/D19))) -> 0.19343593 | E25: =IF(E7="","",IF(OR(E19=0,E16=0),"n/a",IF(((E20+E15/E7)/E16+E11/60*E9)/E19>1,"Never pays",((E20+E15/E7)/E16+E11/60*E9)/E19))) -> 0.19022733 | F25: =IF(F7="","",IF(OR(F19=0,F16=0),"n/a",IF(((F20+F15/F7)/F16+F11/60*F9)/F19>1,"Never pays",((F20+F15/F7)/F16+F11/60*F9)/F19))) -> 0.099971389 | G25: =IF(G7="","",IF(OR(G19=0,G16=0),"n/a",IF(((G20+G15/G7)/G16+G11/60*G9)/G19>1,"Never pays",((G20+G15/G7)/G16+G11/60*G9)/G19)))
B26: Value lost per month if success drops 10 points | C26: =IF(C7="","",0.1*C19*C16*C7) -> 25920 | D26: =IF(D7="","",0.1*D19*D16*D7) -> 25500 | E26: =IF(E7="","",0.1*E19*E16*E7) -> 9333.3333 | F26: =IF(F7="","",0.1*F19*F16*F7) -> 18000 | G26: =IF(G7="","",0.1*G19*G16*G7) | H26: =SUM(C26:G26) -> 78753.333
B27: Verdict | C27: =IF(C7="","",IF(C22>0,"Pays back","Loses money")) -> Pays back | D27: =IF(D7="","",IF(D22>0,"Pays back","Loses money")) -> Pays back | E27: =IF(E7="","",IF(E22>0,"Pays back","Loses money")) -> Pays back | F27: =IF(F7="","",IF(F22>0,"Pays back","Loses money")) -> Pays back | G27: =IF(G7="","",IF(G22>0,"Pays back","Loses money"))
B29: How to read this
B30: · Compare 'AI cost per successful task' with 'Cost per task today'. The gap, after review time and failures, is the value.
B31: · 'Lowest success rate' shows how much quality headroom you have. A small gap between it and today's rate is a risk worth monitoring.
B32: · 'Value lost if success drops 10 points' is usually far larger than any vendor price change. Protect quality before negotiating price.
B33: Technical teams can refine every assumption in the Detailed Model tabs (Rate Card onward).
B35: Reference: typical AI cost per task when unknown (from the Rate Card tab)
A36: Size | B36: Tokens per task | C36: Economy | D36: Standard | E36: Premium
A37: Light | B37: 5000 | C37: =$B37/1000000*(0.85*0.6*'Rate Card'!$B$7+0.85*0.4*'Rate Card'!$C$7+0.15*'Rate Card'!$D$7) -> 0.003235 | D37: =$B37/1000000*(0.85*0.6*'Rate Card'!$B$6+0.85*0.4*'Rate Card'!$C$6+0.15*'Rate Card'!$D$6) -> 0.01294 | E37: =$B37/1000000*(0.85*0.6*'Rate Card'!$B$5+0.85*0.4*'Rate Card'!$C$5+0.15*'Rate Card'!$D$5) -> 0.03235
A38: Medium | B38: 50000 | C38: =$B38/1000000*(0.85*0.6*'Rate Card'!$B$7+0.85*0.4*'Rate Card'!$C$7+0.15*'Rate Card'!$D$7) -> 0.03235 | D38: =$B38/1000000*(0.85*0.6*'Rate Card'!$B$6+0.85*0.4*'Rate Card'!$C$6+0.15*'Rate Card'!$D$6) -> 0.1294 | E38: =$B38/1000000*(0.85*0.6*'Rate Card'!$B$5+0.85*0.4*'Rate Card'!$C$5+0.15*'Rate Card'!$D$5) -> 0.3235
A39: Heavy | B39: 200000 | C39: =$B39/1000000*(0.85*0.6*'Rate Card'!$B$7+0.85*0.4*'Rate Card'!$C$7+0.15*'Rate Card'!$D$7) -> 0.1294 | D39: =$B39/1000000*(0.85*0.6*'Rate Card'!$B$6+0.85*0.4*'Rate Card'!$C$6+0.15*'Rate Card'!$D$6) -> 0.5176 | E39: =$B39/1000000*(0.85*0.6*'Rate Card'!$B$5+0.85*0.4*'Rate Card'!$C$5+0.15*'Rate Card'!$D$5) -> 1.294
B40: Assumes 85% of tokens are input (40% of them cached) and 15% output. Batch processing would halve these.

Sheet Detailed Model Guide
A1: Detailed Model (for finance and technical teams)
A3: Purpose | B3: Measure what GenAI actually costs per unit of business work, and whether that work is worth it. The template moves from list price per million tokens to cost per task, cost per successful outcome, and net value per task, for every production use case.
A4: Worked example | B4: Pre-filled with a fictional 12,000-employee financial services firm running four use cases. All figures are illustrative. Replace them with your own telemetry and contracted rates.
A5: How to use | B5: 1) Rate Card: enter your contracted price per million tokens for each model tier. 2) Platform Costs: enter fixed monthly run costs (gateway, observability, evaluation, retrieval, engineering). 3) Use Cases: one row per production use case; edit only the blue cells. 4) Read Calculator, Portfolio Summary and Sensitivity. 5) Track actuals monthly in Monthly Tracker.
A6: Color legend | B6: Blue text = input you may change. Black = formula, do not overwrite. Green = pulled from another sheet. Yellow fill = key assumption worth validating with data.
A7: Core formula | B7: Token cost per call = [uncached input × input rate + cached input × cached rate + (output + reasoning) × output rate] ÷ 1,000,000 × batch factor. Cost per task = cost per call × calls per task × (1 + retry overhead).
A8: Value logic | B8: Baseline cost per task = baseline human minutes × loaded labor rate. AI-path human cost = review minutes + (failed share × full baseline minutes). Net value per task = (baseline − residual human cost) × value realization − fully loaded AI cost per task.
A9: Allocation | B9: Shared platform costs are allocated to use cases in proportion to token spend. Swap to task count or direct attribution if that better reflects how your platform is consumed.
A10: Not modeled | B10: Cache-write premiums, long-context price tiers, provisioned-throughput or committed-use discounts, fine-tuning, embedding and tool-call fees, and FX. Add rows to Platform Costs or adjust rates if they are material for you.
A11: Prices | B11: Rate Card values are illustrative tiers in the range of 2026 public list prices for frontier, mid and small models. They are not quotes from any vendor.

Sheet Rate Card
A1: Rate Card (USD per 1M tokens)
A2: Illustrative tiers. Replace with your contracted rates, including any committed-use discount.
A4: Model tier | B4: Input $/1M | C4: Cached input $/1M | D4: Output $/1M (incl. reasoning) | E4: Typical use
A5: Frontier | B5: 5 | C5: 0.5 | D5: 25 | E5: Complex reasoning, long documents, high-stakes judgment
A6: Mid | B6: 2 | C6: 0.2 | D6: 10 | E6: Agents, RAG assistants, most production workloads
A7: Small | B7: 0.5 | C7: 0.05 | D7: 2.5 | E7: Classification, routing, extraction, triage
A9: Batch discount | B9: 0.5 | C9: Discount on calls run through an asynchronous batch API
A11: Cached input is typically ~10% of the input rate; output usually costs 4-6x input. Reasoning tokens are billed at the output rate even though users never see them.

Sheet Platform Costs
A1: Shared Platform Run Costs (USD per month)
A2: Fixed costs that exist whether or not a single token is consumed. Allocated to use cases in proportion to token spend.
A4: Cost line | B4: Monthly cost $ | C4: Notes
A5: LLM gateway and observability | B5: 6000 | C5: Routing, rate limiting, logging, per-request cost telemetry
A6: Evaluation and guardrails | B6: 4000 | C6: Eval harness, red-teaming, PII and policy filters
A7: Retrieval infrastructure | B7: 5000 | C7: Vector store, embeddings refresh, document pipelines
A8: Engineering and MLOps (2 FTE, loaded) | B8: 30000 | C8: Prompt maintenance, model upgrades, incident response
A9: Other (add your own) | B9: 0
A10: Total platform cost | B10: =SUM(B5:B9) -> 45000

Sheet Use Cases
A1: Use Case Inputs (one row per production use case)
A2: Worked example: fictional financial services firm. Edit blue cells; rows 9-12 are free for your own use cases.
A4: Use case | B4: Business function | C4: Monthly tasks | D4: Model tier | E4: Model calls per task | F4: Avg input tokens per call | G4: Avg output tokens per call | H4: Avg reasoning tokens per call | I4: Cached share of input | J4: Batch share of calls | K4: Retry / rework overhead | L4: Task success rate | M4: Human review min per task | N4: Baseline human min per task | O4: Loaded labor cost $/hour | P4: Value realization | Q4: Value type
A5: Customer service agent | B5: Client servicing | C5: 60000 | D5: Mid | E5: 6 | F5: 9000 | G5: 400 | H5: 600 | I5: 0.6 | J5: 0 | K5: 0.08 | L5: 0.78 | M5: 1 | N5: 9 | O5: 32 | P5: 0.9 | Q5: Hard: deflected handle time
A6: Contract clause extraction | B6: Procurement / Legal | C6: 3000 | D6: Frontier | E6: 3 | F6: 60000 | G6: 2500 | H6: 4000 | I6: 0.2 | J6: 1 | K6: 0.05 | L6: 0.9 | M6: 12 | N6: 75 | O6: 85 | P6: 0.8 | Q6: Hard: review hours
A7: Invoice exception triage | B7: Accounts payable | C7: 25000 | D7: Small | E7: 2 | F7: 4000 | G7: 300 | H7: 0 | I7: 0.7 | J7: 0.5 | K7: 0.03 | L7: 0.85 | M7: 1.5 | N7: 8 | O7: 28 | P7: 1 | Q7: Hard: AP processing time
A8: Internal knowledge assistant | B8: HR / IT policy Q&A | C8: 150000 | D8: Mid | E8: 1.5 | F8: 7000 | G8: 450 | H8: 300 | I8: 0.4 | J8: 0 | K8: 0.1 | L8: 0.7 | M8: 0 | N8: 4 | O8: 45 | P8: 0.4 | Q8: Soft: time saved searching
A14: Hover over header cells with a red corner for definitions. Token counts should come from API usage metadata or gateway logs, not estimates from word counts.

Sheet Calculator
A1: Calculator (all formulas, do not edit)
A2: Monthly view per use case. Costs in USD.
A4: Use case | B4: Model tier | C4: Effective calls / month | D4: Input tokens / month (M) | E4: Output + reasoning tokens / month (M) | F4: Batch factor | G4: Uncached input cost $ | H4: Cached input cost $ | I4: Output cost $ | J4: Token cost $ / month | K4: Allocated platform $ | L4: Total AI run cost $ | M4: Token cost per task $ | N4: AI cost per task (fully loaded) $ | O4: AI cost per successful task $ | P4: Residual human cost per task $ | Q4: Baseline cost per task $ | R4: Labor saving per task $ | S4: Realized saving per task $ | T4: Net value per task $ | U4: Net value $ / month | V4: ROI on AI run cost | W4: Break-even token cost per task $ | X4: Token cost headroom | Y4: Tokens per task (k) | Z4: Output share of token cost | AA4: Realized saving $ / month
A5: =IF('Use Cases'!A5="","",'Use Cases'!A5) -> Customer service agent | B5: =IF('Use Cases'!D5="","",'Use Cases'!D5) -> Mid | C5: ='Use Cases'!C5*'Use Cases'!E5*(1+'Use Cases'!K5) -> 388800 | D5: =C5*'Use Cases'!F5/1000000 -> 3499.2 | E5: =C5*('Use Cases'!G5+'Use Cases'!H5)/1000000 -> 388.8 | F5: =1-'Use Cases'!J5*'Rate Card'!$B$9 -> 1 | G5: =IF(B5="",0,D5*(1-'Use Cases'!I5)*INDEX('Rate Card'!$B$5:$B$7,MATCH('Use Cases'!$D5,'Rate Card'!$A$5:$A$7,0))*F5) -> 2799.36 | H5: =IF(B5="",0,D5*'Use Cases'!I5*INDEX('Rate Card'!$C$5:$C$7,MATCH('Use Cases'!$D5,'Rate Card'!$A$5:$A$7,0))*F5) -> 419.904 | I5: =IF(B5="",0,E5*INDEX('Rate Card'!$D$5:$D$7,MATCH('Use Cases'!$D5,'Rate Card'!$A$5:$A$7,0))*F5) -> 3888 | J5: =G5+H5+I5 -> 7107.264 | K5: =IF($J$13=0,0,J5/$J$13*'Platform Costs'!$B$10) -> 24286.663 | L5: =J5+K5 -> 31393.927 | M5: =IF('Use Cases'!C5=0,0,J5/'Use Cases'!C5) -> 0.1184544 | N5: =IF('Use Cases'!C5=0,0,L5/'Use Cases'!C5) -> 0.52323211 | O5: =IF('Use Cases'!L5=0,0,N5/'Use Cases'!L5) -> 0.6708104 | P5: =('Use Cases'!M5+(1-'Use Cases'!L5)*'Use Cases'!N5)/60*'Use Cases'!O5 -> 1.5893333 | Q5: ='Use Cases'!N5/60*'Use Cases'!O5 -> 4.8 | R5: =Q5-P5 -> 3.2106667 | S5: =R5*'Use Cases'!P5 -> 2.8896 | T5: =S5-N5 -> 2.3663679 | U5: =T5*'Use Cases'!C5 -> 141982.07 | V5: =IF(L5=0,0,U5/L5) -> 4.5225968 | W5: =M5+T5 -> 2.4848223 | X5: =IF(M5=0,0,W5/M5) -> 20.977037 | Y5: ='Use Cases'!E5*(1+'Use Cases'!K5)*('Use Cases'!F5+'Use Cases'!G5+'Use Cases'!H5)/1000 -> 64.8 | Z5: =IF(J5=0,0,I5/J5) -> 0.54704595 | AA5: =S5*'Use Cases'!C5 -> 173376
A6: =IF('Use Cases'!A6="","",'Use Cases'!A6) -> Contract clause extraction | B6: =IF('Use Cases'!D6="","",'Use Cases'!D6) -> Frontier | C6: ='Use Cases'!C6*'Use Cases'!E6*(1+'Use Cases'!K6) -> 9450 | D6: =C6*'Use Cases'!F6/1000000 -> 567 | E6: =C6*('Use Cases'!G6+'Use Cases'!H6)/1000000 -> 61.425 | F6: =1-'Use Cases'!J6*'Rate Card'!$B$9 -> 0.5 | G6: =IF(B6="",0,D6*(1-'Use Cases'!I6)*INDEX('Rate Card'!$B$5:$B$7,MATCH('Use Cases'!$D6,'Rate Card'!$A$5:$A$7,0))*F6) -> 1134 | H6: =IF(B6="",0,D6*'Use Cases'!I6*INDEX('Rate Card'!$C$5:$C$7,MATCH('Use Cases'!$D6,'Rate Card'!$A$5:$A$7,0))*F6) -> 28.35 | I6: =IF(B6="",0,E6*INDEX('Rate Card'!$D$5:$D$7,MATCH('Use Cases'!$D6,'Rate Card'!$A$5:$A$7,0))*F6) -> 767.8125 | J6: =G6+H6+I6 -> 1930.1625 | K6: =IF($J$13=0,0,J6/$J$13*'Platform Costs'!$B$10) -> 6595.6753 | L6: =J6+K6 -> 8525.8378 | M6: =IF('Use Cases'!C6=0,0,J6/'Use Cases'!C6) -> 0.6433875 | N6: =IF('Use Cases'!C6=0,0,L6/'Use Cases'!C6) -> 2.8419459 | O6: =IF('Use Cases'!L6=0,0,N6/'Use Cases'!L6) -> 3.1577177 | P6: =('Use Cases'!M6+(1-'Use Cases'!L6)*'Use Cases'!N6)/60*'Use Cases'!O6 -> 27.625 | Q6: ='Use Cases'!N6/60*'Use Cases'!O6 -> 106.25 | R6: =Q6-P6 -> 78.625 | S6: =R6*'Use Cases'!P6 -> 62.9 | T6: =S6-N6 -> 60.058054 | U6: =T6*'Use Cases'!C6 -> 180174.16 | V6: =IF(L6=0,0,U6/L6) -> 21.132722 | W6: =M6+T6 -> 60.701442 | X6: =IF(M6=0,0,W6/M6) -> 94.346629 | Y6: ='Use Cases'!E6*(1+'Use Cases'!K6)*('Use Cases'!F6+'Use Cases'!G6+'Use Cases'!H6)/1000 -> 209.475 | Z6: =IF(J6=0,0,I6/J6) -> 0.39779682 | AA6: =S6*'Use Cases'!C6 -> 188700
A7: =IF('Use Cases'!A7="","",'Use Cases'!A7) -> Invoice exception triage | B7: =IF('Use Cases'!D7="","",'Use Cases'!D7) -> Small | C7: ='Use Cases'!C7*'Use Cases'!E7*(1+'Use Cases'!K7) -> 51500 | D7: =C7*'Use Cases'!F7/1000000 -> 206 | E7: =C7*('Use Cases'!G7+'Use Cases'!H7)/1000000 -> 15.45 | F7: =1-'Use Cases'!J7*'Rate Card'!$B$9 -> 0.75 | G7: =IF(B7="",0,D7*(1-'Use Cases'!I7)*INDEX('Rate Card'!$B$5:$B$7,MATCH('Use Cases'!$D7,'Rate Card'!$A$5:$A$7,0))*F7) -> 23.175 | H7: =IF(B7="",0,D7*'Use Cases'!I7*INDEX('Rate Card'!$C$5:$C$7,MATCH('Use Cases'!$D7,'Rate Card'!$A$5:$A$7,0))*F7) -> 5.4075 | I7: =IF(B7="",0,E7*INDEX('Rate Card'!$D$5:$D$7,MATCH('Use Cases'!$D7,'Rate Card'!$A$5:$A$7,0))*F7) -> 28.96875 | J7: =G7+H7+I7 -> 57.55125 | K7: =IF($J$13=0,0,J7/$J$13*'Platform Costs'!$B$10) -> 196.66187 | L7: =J7+K7 -> 254.21312 | M7: =IF('Use Cases'!C7=0,0,J7/'Use Cases'!C7) -> 0.00230205 | N7: =IF('Use Cases'!C7=0,0,L7/'Use Cases'!C7) -> 0.010168525 | O7: =IF('Use Cases'!L7=0,0,N7/'Use Cases'!L7) -> 0.01196297 | P7: =('Use Cases'!M7+(1-'Use Cases'!L7)*'Use Cases'!N7)/60*'Use Cases'!O7 -> 1.26 | Q7: ='Use Cases'!N7/60*'Use Cases'!O7 -> 3.7333333 | R7: =Q7-P7 -> 2.4733333 | S7: =R7*'Use Cases'!P7 -> 2.4733333 | T7: =S7-N7 -> 2.4631648 | U7: =T7*'Use Cases'!C7 -> 61579.12 | V7: =IF(L7=0,0,U7/L7) -> 242.23424 | W7: =M7+T7 -> 2.4654669 | X7: =IF(M7=0,0,W7/M7) -> 1070.9875 | Y7: ='Use Cases'!E7*(1+'Use Cases'!K7)*('Use Cases'!F7+'Use Cases'!G7+'Use Cases'!H7)/1000 -> 8.858 | Z7: =IF(J7=0,0,I7/J7) -> 0.5033557 | AA7: =S7*'Use Cases'!C7 -> 61833.333
A8: =IF('Use Cases'!A8="","",'Use Cases'!A8) -> Internal knowledge assistant | B8: =IF('Use Cases'!D8="","",'Use Cases'!D8) -> Mid | C8: ='Use Cases'!C8*'Use Cases'!E8*(1+'Use Cases'!K8) -> 247500 | D8: =C8*'Use Cases'!F8/1000000 -> 1732.5 | E8: =C8*('Use Cases'!G8+'Use Cases'!H8)/1000000 -> 185.625 | F8: =1-'Use Cases'!J8*'Rate Card'!$B$9 -> 1 | G8: =IF(B8="",0,D8*(1-'Use Cases'!I8)*INDEX('Rate Card'!$B$5:$B$7,MATCH('Use Cases'!$D8,'Rate Card'!$A$5:$A$7,0))*F8) -> 2079 | H8: =IF(B8="",0,D8*'Use Cases'!I8*INDEX('Rate Card'!$C$5:$C$7,MATCH('Use Cases'!$D8,'Rate Card'!$A$5:$A$7,0))*F8) -> 138.6 | I8: =IF(B8="",0,E8*INDEX('Rate Card'!$D$5:$D$7,MATCH('Use Cases'!$D8,'Rate Card'!$A$5:$A$7,0))*F8) -> 1856.25 | J8: =G8+H8+I8 -> 4073.85 | K8: =IF($J$13=0,0,J8/$J$13*'Platform Costs'!$B$10) -> 13921 | L8: =J8+K8 -> 17994.85 | M8: =IF('Use Cases'!C8=0,0,J8/'Use Cases'!C8) -> 0.027159 | N8: =IF('Use Cases'!C8=0,0,L8/'Use Cases'!C8) -> 0.11996567 | O8: =IF('Use Cases'!L8=0,0,N8/'Use Cases'!L8) -> 0.17137952 | P8: =('Use Cases'!M8+(1-'Use Cases'!L8)*'Use Cases'!N8)/60*'Use Cases'!O8 -> 0.9 | Q8: ='Use Cases'!N8/60*'Use Cases'!O8 -> 3 | R8: =Q8-P8 -> 2.1 | S8: =R8*'Use Cases'!P8 -> 0.84 | T8: =S8-N8 -> 0.72003433 | U8: =T8*'Use Cases'!C8 -> 108005.15 | V8: =IF(L8=0,0,U8/L8) -> 6.0020034 | W8: =M8+T8 -> 0.74719333 | X8: =IF(M8=0,0,W8/M8) -> 27.511813 | Y8: ='Use Cases'!E8*(1+'Use Cases'!K8)*('Use Cases'!F8+'Use Cases'!G8+'Use Cases'!H8)/1000 -> 12.7875 | Z8: =IF(J8=0,0,I8/J8) -> 0.45565006 | AA8: =S8*'Use Cases'!C8 -> 126000
A9: =IF('Use Cases'!A9="","",'Use Cases'!A9) | B9: =IF('Use Cases'!D9="","",'Use Cases'!D9) | C9: ='Use Cases'!C9*'Use Cases'!E9*(1+'Use Cases'!K9) -> 0 | D9: =C9*'Use Cases'!F9/1000000 -> 0 | E9: =C9*('Use Cases'!G9+'Use Cases'!H9)/1000000 -> 0 | F9: =1-'Use Cases'!J9*'Rate Card'!$B$9 -> 1 | G9: =IF(B9="",0,D9*(1-'Use Cases'!I9)*INDEX('Rate Card'!$B$5:$B$7,MATCH('Use Cases'!$D9,'Rate Card'!$A$5:$A$7,0))*F9) -> 0 | H9: =IF(B9="",0,D9*'Use Cases'!I9*INDEX('Rate Card'!$C$5:$C$7,MATCH('Use Cases'!$D9,'Rate Card'!$A$5:$A$7,0))*F9) -> 0 | I9: =IF(B9="",0,E9*INDEX('Rate Card'!$D$5:$D$7,MATCH('Use Cases'!$D9,'Rate Card'!$A$5:$A$7,0))*F9) -> 0 | J9: =G9+H9+I9 -> 0 | K9: =IF($J$13=0,0,J9/$J$13*'Platform Costs'!$B$10) -> 0 | L9: =J9+K9 -> 0 | M9: =IF('Use Cases'!C9=0,0,J9/'Use Cases'!C9) -> 0 | N9: =IF('Use Cases'!C9=0,0,L9/'Use Cases'!C9) -> 0 | O9: =IF('Use Cases'!L9=0,0,N9/'Use Cases'!L9) -> 0 | P9: =('Use Cases'!M9+(1-'Use Cases'!L9)*'Use Cases'!N9)/60*'Use Cases'!O9 -> 0 | Q9: ='Use Cases'!N9/60*'Use Cases'!O9 -> 0 | R9: =Q9-P9 -> 0 | S9: =R9*'Use Cases'!P9 -> 0 | T9: =S9-N9 -> 0 | U9: =T9*'Use Cases'!C9 -> 0 | V9: =IF(L9=0,0,U9/L9) -> 0 | W9: =M9+T9 -> 0 | X9: =IF(M9=0,0,W9/M9) -> 0 | Y9: ='Use Cases'!E9*(1+'Use Cases'!K9)*('Use Cases'!F9+'Use Cases'!G9+'Use Cases'!H9)/1000 -> 0 | Z9: =IF(J9=0,0,I9/J9) -> 0 | AA9: =S9*'Use Cases'!C9 -> 0
A10: =IF('Use Cases'!A10="","",'Use Cases'!A10) | B10: =IF('Use Cases'!D10="","",'Use Cases'!D10) | C10: ='Use Cases'!C10*'Use Cases'!E10*(1+'Use Cases'!K10) -> 0 | D10: =C10*'Use Cases'!F10/1000000 -> 0 | E10: =C10*('Use Cases'!G10+'Use Cases'!H10)/1000000 -> 0 | F10: =1-'Use Cases'!J10*'Rate Card'!$B$9 -> 1 | G10: =IF(B10="",0,D10*(1-'Use Cases'!I10)*INDEX('Rate Card'!$B$5:$B$7,MATCH('Use Cases'!$D10,'Rate Card'!$A$5:$A$7,0))*F10) -> 0 | H10: =IF(B10="",0,D10*'Use Cases'!I10*INDEX('Rate Card'!$C$5:$C$7,MATCH('Use Cases'!$D10,'Rate Card'!$A$5:$A$7,0))*F10) -> 0 | I10: =IF(B10="",0,E10*INDEX('Rate Card'!$D$5:$D$7,MATCH('Use Cases'!$D10,'Rate Card'!$A$5:$A$7,0))*F10) -> 0 | J10: =G10+H10+I10 -> 0 | K10: =IF($J$13=0,0,J10/$J$13*'Platform Costs'!$B$10) -> 0 | L10: =J10+K10 -> 0 | M10: =IF('Use Cases'!C10=0,0,J10/'Use Cases'!C10) -> 0 | N10: =IF('Use Cases'!C10=0,0,L10/'Use Cases'!C10) -> 0 | O10: =IF('Use Cases'!L10=0,0,N10/'Use Cases'!L10) -> 0 | P10: =('Use Cases'!M10+(1-'Use Cases'!L10)*'Use Cases'!N10)/60*'Use Cases'!O10 -> 0 | Q10: ='Use Cases'!N10/60*'Use Cases'!O10 -> 0 | R10: =Q10-P10 -> 0 | S10: =R10*'Use Cases'!P10 -> 0 | T10: =S10-N10 -> 0 | U10: =T10*'Use Cases'!C10 -> 0 | V10: =IF(L10=0,0,U10/L10) -> 0 | W10: =M10+T10 -> 0 | X10: =IF(M10=0,0,W10/M10) -> 0 | Y10: ='Use Cases'!E10*(1+'Use Cases'!K10)*('Use Cases'!F10+'Use Cases'!G10+'Use Cases'!H10)/1000 -> 0 | Z10: =IF(J10=0,0,I10/J10) -> 0 | AA10: =S10*'Use Cases'!C10 -> 0
A11: =IF('Use Cases'!A11="","",'Use Cases'!A11) | B11: =IF('Use Cases'!D11="","",'Use Cases'!D11) | C11: ='Use Cases'!C11*'Use Cases'!E11*(1+'Use Cases'!K11) -> 0 | D11: =C11*'Use Cases'!F11/1000000 -> 0 | E11: =C11*('Use Cases'!G11+'Use Cases'!H11)/1000000 -> 0 | F11: =1-'Use Cases'!J11*'Rate Card'!$B$9 -> 1 | G11: =IF(B11="",0,D11*(1-'Use Cases'!I11)*INDEX('Rate Card'!$B$5:$B$7,MATCH('Use Cases'!$D11,'Rate Card'!$A$5:$A$7,0))*F11) -> 0 | H11: =IF(B11="",0,D11*'Use Cases'!I11*INDEX('Rate Card'!$C$5:$C$7,MATCH('Use Cases'!$D11,'Rate Card'!$A$5:$A$7,0))*F11) -> 0 | I11: =IF(B11="",0,E11*INDEX('Rate Card'!$D$5:$D$7,MATCH('Use Cases'!$D11,'Rate Card'!$A$5:$A$7,0))*F11) -> 0 | J11: =G11+H11+I11 -> 0 | K11: =IF($J$13=0,0,J11/$J$13*'Platform Costs'!$B$10) -> 0 | L11: =J11+K11 -> 0 | M11: =IF('Use Cases'!C11=0,0,J11/'Use Cases'!C11) -> 0 | N11: =IF('Use Cases'!C11=0,0,L11/'Use Cases'!C11) -> 0 | O11: =IF('Use Cases'!L11=0,0,N11/'Use Cases'!L11) -> 0 | P11: =('Use Cases'!M11+(1-'Use Cases'!L11)*'Use Cases'!N11)/60*'Use Cases'!O11 -> 0 | Q11: ='Use Cases'!N11/60*'Use Cases'!O11 -> 0 | R11: =Q11-P11 -> 0 | S11: =R11*'Use Cases'!P11 -> 0 | T11: =S11-N11 -> 0 | U11: =T11*'Use Cases'!C11 -> 0 | V11: =IF(L11=0,0,U11/L11) -> 0 | W11: =M11+T11 -> 0 | X11: =IF(M11=0,0,W11/M11) -> 0 | Y11: ='Use Cases'!E11*(1+'Use Cases'!K11)*('Use Cases'!F11+'Use Cases'!G11+'Use Cases'!H11)/1000 -> 0 | Z11: =IF(J11=0,0,I11/J11) -> 0 | AA11: =S11*'Use Cases'!C11 -> 0
A12: =IF('Use Cases'!A12="","",'Use Cases'!A12) | B12: =IF('Use Cases'!D12="","",'Use Cases'!D12) | C12: ='Use Cases'!C12*'Use Cases'!E12*(1+'Use Cases'!K12) -> 0 | D12: =C12*'Use Cases'!F12/1000000 -> 0 | E12: =C12*('Use Cases'!G12+'Use Cases'!H12)/1000000 -> 0 | F12: =1-'Use Cases'!J12*'Rate Card'!$B$9 -> 1 | G12: =IF(B12="",0,D12*(1-'Use Cases'!I12)*INDEX('Rate Card'!$B$5:$B$7,MATCH('Use Cases'!$D12,'Rate Card'!$A$5:$A$7,0))*F12) -> 0 | H12: =IF(B12="",0,D12*'Use Cases'!I12*INDEX('Rate Card'!$C$5:$C$7,MATCH('Use Cases'!$D12,'Rate Card'!$A$5:$A$7,0))*F12) -> 0 | I12: =IF(B12="",0,E12*INDEX('Rate Card'!$D$5:$D$7,MATCH('Use Cases'!$D12,'Rate Card'!$A$5:$A$7,0))*F12) -> 0 | J12: =G12+H12+I12 -> 0 | K12: =IF($J$13=0,0,J12/$J$13*'Platform Costs'!$B$10) -> 0 | L12: =J12+K12 -> 0 | M12: =IF('Use Cases'!C12=0,0,J12/'Use Cases'!C12) -> 0 | N12: =IF('Use Cases'!C12=0,0,L12/'Use Cases'!C12) -> 0 | O12: =IF('Use Cases'!L12=0,0,N12/'Use Cases'!L12) -> 0 | P12: =('Use Cases'!M12+(1-'Use Cases'!L12)*'Use Cases'!N12)/60*'Use Cases'!O12 -> 0 | Q12: ='Use Cases'!N12/60*'Use Cases'!O12 -> 0 | R12: =Q12-P12 -> 0 | S12: =R12*'Use Cases'!P12 -> 0 | T12: =S12-N12 -> 0 | U12: =T12*'Use Cases'!C12 -> 0 | V12: =IF(L12=0,0,U12/L12) -> 0 | W12: =M12+T12 -> 0 | X12: =IF(M12=0,0,W12/M12) -> 0 | Y12: ='Use Cases'!E12*(1+'Use Cases'!K12)*('Use Cases'!F12+'Use Cases'!G12+'Use Cases'!H12)/1000 -> 0 | Z12: =IF(J12=0,0,I12/J12) -> 0 | AA12: =S12*'Use Cases'!C12 -> 0
A13: Portfolio total | C13: =SUM(C5:C12) -> 697250 | D13: =SUM(D5:D12) -> 6004.7 | E13: =SUM(E5:E12) -> 651.3 | G13: =SUM(G5:G12) -> 6035.535 | H13: =SUM(H5:H12) -> 592.2615 | I13: =SUM(I5:I12) -> 6541.0312 | J13: =SUM(J5:J12) -> 13168.828 | K13: =SUM(K5:K12) -> 45000 | L13: =SUM(L5:L12) -> 58168.828 | U13: =SUM(U5:U12) -> 491740.51 | V13: =IF(L13=0,0,U13/L13) -> 8.4536774 | AA13: =SUM(AA5:AA12) -> 549909.33

Sheet Portfolio Summary
A1: Portfolio Summary
A2: The numbers a CFO or category manager should see each month.
A4: Metric | B4: Value | C4: How to read it
A5: Monthly tasks served | B5: =SUM('Use Cases'!C5:C12) -> 238000 | C5: Business units of work, not API calls
A6: Effective model calls per month | B6: =Calculator!C13 -> 697250 | C6: Includes agent steps and retries
A7: Input tokens per month (M) | B7: =Calculator!D13 -> 6004.7
A8: Output + reasoning tokens per month (M) | B8: =Calculator!E13 -> 651.3
A9: Token cost per month $ | B9: =Calculator!J13 -> 13168.828 | C9: The vendor invoice
A10: Shared platform cost per month $ | B10: =Calculator!K13 -> 45000 | C10: Usually invisible in vendor-only views
A11: Total AI run cost per month $ | B11: =Calculator!L13 -> 58168.828 | C11: Token cost plus platform
A12: Token share of AI run cost | B12: =IF(Calculator!L13=0,0,Calculator!J13/Calculator!L13) -> 0.22638977 | C12: Below ~50% means scale, not price, is the main lever
A13: Blended AI cost per task $ | B13: =IF(B5=0,0,Calculator!L13/B5) -> 0.24440684
A14: Effective cache hit rate | B14: =IF(Calculator!D13=0,0,SUMPRODUCT(Calculator!D5:D12,'Use Cases'!I5:I12)/Calculator!D13) -> 0.50795543 | C14: Weighted by input volume
A15: Output share of token cost | B15: =IF(Calculator!J13=0,0,Calculator!I13/Calculator!J13) -> 0.49670566 | C15: High share points to verbosity or reasoning load
A16: Largest use case share of token cost | B16: =IF(Calculator!J13=0,0,MAX(Calculator!J5:J12)/Calculator!J13) -> 0.53970362 | C16: Concentration risk on one workload
A17: Net value per month $ | B17: =Calculator!U13 -> 491740.51 | C17: After realization haircut and all AI costs
A18: Net value per year $ | B18: =B17*12 -> 5900886.1
A19: ROI on AI run cost | B19: =Calculator!V13 -> 8.4536774 | C19: Net value per dollar of AI run cost
A21: Token cost by model tier
A22: Tier | B22: Token cost $ / month | C22: Share
A23: ='Rate Card'!A5 -> Frontier | B23: =SUMIF(Calculator!B5:B12,A23,Calculator!J5:J12) -> 1930.1625 | C23: =IF(Calculator!J13=0,0,B23/Calculator!J13) -> 0.14657056
A24: ='Rate Card'!A6 -> Mid | B24: =SUMIF(Calculator!B5:B12,A24,Calculator!J5:J12) -> 11181.114 | C24: =IF(Calculator!J13=0,0,B24/Calculator!J13) -> 0.84905917
A25: ='Rate Card'!A7 -> Small | B25: =SUMIF(Calculator!B5:B12,A25,Calculator!J5:J12) -> 57.55125 | C25: =IF(Calculator!J13=0,0,B25/Calculator!J13) -> 0.0043702637

Sheet Sensitivity
A1: Sensitivity and Optimization Levers
A2: Each row changes one driver and holds everything else at the worked-example values. Levers are not strictly additive.
A4: Lever settings
A5: Vendor price increase | B5: 0.3
A6: Vendor price cut | B6: 0.4
A7: Volume multiplier | B7: 3
A8: Input context trimmed by | B8: 0.25
A9: Cache hit uplift (points) | B9: 0.2
A10: Output tokens reduced by | B10: 0.3
A11: Cache hit ceiling | B11: 0.95
A12: Task success rate drop (points) | B12: 0.1
A14: Per use case helper
A15: Use case | B15: Route to Small tier? (Y/N) | C15: Token cost $ now | D15: Token cost $ on Small tier | E15: Routing saving $ | F15: Cache uplift saving $
A16: =Calculator!A5 -> Customer service agent | B16: N | C16: =Calculator!J5 -> 7107.264 | D16: =(Calculator!D5*(1-'Use Cases'!I5)*'Rate Card'!$B$7+Calculator!D5*'Use Cases'!I5*'Rate Card'!$C$7+Calculator!E5*'Rate Card'!$D$7)*Calculator!F5 -> 1776.816 | E16: =IF(B16="Y",C16-D16,0) -> 0 | F16: =IF(Calculator!B5="",0,MAX(0,MIN($B$9,$B$11-'Use Cases'!I5))*Calculator!D5*(INDEX('Rate Card'!$B$5:$B$7,MATCH(Calculator!B5,'Rate Card'!$A$5:$A$7,0))-INDEX('Rate Card'!$C$5:$C$7,MATCH(Calculator!B5,'Rate Card'!$A$5:$A$7,0)))*Calculator!F5) -> 1259.712
A17: =Calculator!A6 -> Contract clause extraction | B17: N | C17: =Calculator!J6 -> 1930.1625 | D17: =(Calculator!D6*(1-'Use Cases'!I6)*'Rate Card'!$B$7+Calculator!D6*'Use Cases'!I6*'Rate Card'!$C$7+Calculator!E6*'Rate Card'!$D$7)*Calculator!F6 -> 193.01625 | E17: =IF(B17="Y",C17-D17,0) -> 0 | F17: =IF(Calculator!B6="",0,MAX(0,MIN($B$9,$B$11-'Use Cases'!I6))*Calculator!D6*(INDEX('Rate Card'!$B$5:$B$7,MATCH(Calculator!B6,'Rate Card'!$A$5:$A$7,0))-INDEX('Rate Card'!$C$5:$C$7,MATCH(Calculator!B6,'Rate Card'!$A$5:$A$7,0)))*Calculator!F6) -> 255.15
A18: =Calculator!A7 -> Invoice exception triage | B18: N | C18: =Calculator!J7 -> 57.55125 | D18: =(Calculator!D7*(1-'Use Cases'!I7)*'Rate Card'!$B$7+Calculator!D7*'Use Cases'!I7*'Rate Card'!$C$7+Calculator!E7*'Rate Card'!$D$7)*Calculator!F7 -> 57.55125 | E18: =IF(B18="Y",C18-D18,0) -> 0 | F18: =IF(Calculator!B7="",0,MAX(0,MIN($B$9,$B$11-'Use Cases'!I7))*Calculator!D7*(INDEX('Rate Card'!$B$5:$B$7,MATCH(Calculator!B7,'Rate Card'!$A$5:$A$7,0))-INDEX('Rate Card'!$C$5:$C$7,MATCH(Calculator!B7,'Rate Card'!$A$5:$A$7,0)))*Calculator!F7) -> 13.905
A19: =Calculator!A8 -> Internal knowledge assistant | B19: Y | C19: =Calculator!J8 -> 4073.85 | D19: =(Calculator!D8*(1-'Use Cases'!I8)*'Rate Card'!$B$7+Calculator!D8*'Use Cases'!I8*'Rate Card'!$C$7+Calculator!E8*'Rate Card'!$D$7)*Calculator!F8 -> 1018.4625 | E19: =IF(B19="Y",C19-D19,0) -> 3055.3875 | F19: =IF(Calculator!B8="",0,MAX(0,MIN($B$9,$B$11-'Use Cases'!I8))*Calculator!D8*(INDEX('Rate Card'!$B$5:$B$7,MATCH(Calculator!B8,'Rate Card'!$A$5:$A$7,0))-INDEX('Rate Card'!$C$5:$C$7,MATCH(Calculator!B8,'Rate Card'!$A$5:$A$7,0)))*Calculator!F8) -> 623.7
A20: =Calculator!A9 | B20: N | C20: =Calculator!J9 -> 0 | D20: =(Calculator!D9*(1-'Use Cases'!I9)*'Rate Card'!$B$7+Calculator!D9*'Use Cases'!I9*'Rate Card'!$C$7+Calculator!E9*'Rate Card'!$D$7)*Calculator!F9 -> 0 | E20: =IF(B20="Y",C20-D20,0) -> 0 | F20: =IF(Calculator!B9="",0,MAX(0,MIN($B$9,$B$11-'Use Cases'!I9))*Calculator!D9*(INDEX('Rate Card'!$B$5:$B$7,MATCH(Calculator!B9,'Rate Card'!$A$5:$A$7,0))-INDEX('Rate Card'!$C$5:$C$7,MATCH(Calculator!B9,'Rate Card'!$A$5:$A$7,0)))*Calculator!F9) -> 0
A21: =Calculator!A10 | B21: N | C21: =Calculator!J10 -> 0 | D21: =(Calculator!D10*(1-'Use Cases'!I10)*'Rate Card'!$B$7+Calculator!D10*'Use Cases'!I10*'Rate Card'!$C$7+Calculator!E10*'Rate Card'!$D$7)*Calculator!F10 -> 0 | E21: =IF(B21="Y",C21-D21,0) -> 0 | F21: =IF(Calculator!B10="",0,MAX(0,MIN($B$9,$B$11-'Use Cases'!I10))*Calculator!D10*(INDEX('Rate Card'!$B$5:$B$7,MATCH(Calculator!B10,'Rate Card'!$A$5:$A$7,0))-INDEX('Rate Card'!$C$5:$C$7,MATCH(Calculator!B10,'Rate Card'!$A$5:$A$7,0)))*Calculator!F10) -> 0
A22: =Calculator!A11 | B22: N | C22: =Calculator!J11 -> 0 | D22: =(Calculator!D11*(1-'Use Cases'!I11)*'Rate Card'!$B$7+Calculator!D11*'Use Cases'!I11*'Rate Card'!$C$7+Calculator!E11*'Rate Card'!$D$7)*Calculator!F11 -> 0 | E22: =IF(B22="Y",C22-D22,0) -> 0 | F22: =IF(Calculator!B11="",0,MAX(0,MIN($B$9,$B$11-'Use Cases'!I11))*Calculator!D11*(INDEX('Rate Card'!$B$5:$B$7,MATCH(Calculator!B11,'Rate Card'!$A$5:$A$7,0))-INDEX('Rate Card'!$C$5:$C$7,MATCH(Calculator!B11,'Rate Card'!$A$5:$A$7,0)))*Calculator!F11) -> 0
A23: =Calculator!A12 | B23: N | C23: =Calculator!J12 -> 0 | D23: =(Calculator!D12*(1-'Use Cases'!I12)*'Rate Card'!$B$7+Calculator!D12*'Use Cases'!I12*'Rate Card'!$C$7+Calculator!E12*'Rate Card'!$D$7)*Calculator!F12 -> 0 | E23: =IF(B23="Y",C23-D23,0) -> 0 | F23: =IF(Calculator!B12="",0,MAX(0,MIN($B$9,$B$11-'Use Cases'!I12))*Calculator!D12*(INDEX('Rate Card'!$B$5:$B$7,MATCH(Calculator!B12,'Rate Card'!$A$5:$A$7,0))-INDEX('Rate Card'!$C$5:$C$7,MATCH(Calculator!B12,'Rate Card'!$A$5:$A$7,0)))*Calculator!F12) -> 0
A24: Total | C24: =SUM(C16:C23) -> 13168.828 | D24: =SUM(D16:D23) -> 3045.846 | E24: =SUM(E16:E23) -> 3055.3875 | F24: =SUM(F16:F23) -> 2152.467
A27: Scenario results
A28: Scenario | B28: Token cost $ / month | C28: Total AI run cost $ / month | D28: AI cost per task $ | E28: Net value $ / month | F28: Change in net value vs base $
A29: Base (worked example) | B29: =Calculator!$J$13 -> 13168.828 | C29: =B29+'Platform Costs'!$B$10 -> 58168.828 | D29: =IF(SUM('Use Cases'!$C$5:$C$12)=0,0,C29/SUM('Use Cases'!$C$5:$C$12)) -> 0.24440684 | E29: =Calculator!$AA$13-C29 -> 491740.51 | F29: =E29-$E$29 -> 0
A30: Vendor price increase | B30: =Calculator!$J$13*(1+$B$5) -> 17119.476 | C30: =B30+'Platform Costs'!$B$10 -> 62119.476 | D30: =IF(SUM('Use Cases'!$C$5:$C$12)=0,0,C30/SUM('Use Cases'!$C$5:$C$12)) -> 0.2610062 | E30: =Calculator!$AA$13-C30 -> 487789.86 | F30: =E30-$E$29 -> -3950.6483
A31: Vendor price cut | B31: =Calculator!$J$13*(1-$B$6) -> 7901.2967 | C31: =B31+'Platform Costs'!$B$10 -> 52901.297 | D31: =IF(SUM('Use Cases'!$C$5:$C$12)=0,0,C31/SUM('Use Cases'!$C$5:$C$12)) -> 0.22227436 | E31: =Calculator!$AA$13-C31 -> 497008.04 | F31: =E31-$E$29 -> 5267.5311
A32: Volume multiplied | B32: =Calculator!$J$13*$B$7 -> 39506.483 | C32: =B32+'Platform Costs'!$B$10 -> 84506.483 | D32: =IF(SUM('Use Cases'!$C$5:$C$12)=0,0,C32/(SUM('Use Cases'!$C$5:$C$12)*$B$7)) -> 0.11835642 | E32: =Calculator!$AA$13*$B$7-C32 -> 1565221.5 | F32: =E32-$E$29 -> 1073481
A33: Input context trimmed | B33: =Calculator!$J$13-$B$8*(Calculator!$G$13+Calculator!$H$13) -> 11511.879 | C33: =B33+'Platform Costs'!$B$10 -> 56511.879 | D33: =IF(SUM('Use Cases'!$C$5:$C$12)=0,0,C33/SUM('Use Cases'!$C$5:$C$12)) -> 0.23744487 | E33: =Calculator!$AA$13-C33 -> 493397.45 | F33: =E33-$E$29 -> 1656.9491
A34: Cache hit rate raised | B34: =Calculator!$J$13-$F$24 -> 11016.361 | C34: =B34+'Platform Costs'!$B$10 -> 56016.361 | D34: =IF(SUM('Use Cases'!$C$5:$C$12)=0,0,C34/SUM('Use Cases'!$C$5:$C$12)) -> 0.23536286 | E34: =Calculator!$AA$13-C34 -> 493892.97 | F34: =E34-$E$29 -> 2152.467
A35: Output tokens reduced | B35: =Calculator!$J$13-$B$10*Calculator!$I$13 -> 11206.518 | C35: =B35+'Platform Costs'!$B$10 -> 56206.518 | D35: =IF(SUM('Use Cases'!$C$5:$C$12)=0,0,C35/SUM('Use Cases'!$C$5:$C$12)) -> 0.23616184 | E35: =Calculator!$AA$13-C35 -> 493702.81 | F35: =E35-$E$29 -> 1962.3094
A36: Flagged use cases routed to Small tier | B36: =Calculator!$J$13-$E$24 -> 10113.44 | C36: =B36+'Platform Costs'!$B$10 -> 55113.44 | D36: =IF(SUM('Use Cases'!$C$5:$C$12)=0,0,C36/SUM('Use Cases'!$C$5:$C$12)) -> 0.23156908 | E36: =Calculator!$AA$13-C36 -> 494795.89 | F36: =E36-$E$29 -> 3055.3875
A37: Task success rate lower | B37: =Calculator!$J$13 -> 13168.828 | C37: =B37+'Platform Costs'!$B$10 -> 58168.828 | D37: =IF(SUM('Use Cases'!$C$5:$C$12)=0,0,C37/SUM('Use Cases'!$C$5:$C$12)) -> 0.24440684 | E37: =Calculator!$AA$13-C37-$B$12*SUMPRODUCT('Use Cases'!$C$5:$C$12,Calculator!$Q$5:$Q$12,'Use Cases'!$P$5:$P$12) -> 412987.17 | F37: =E37-$E$29 -> -78753.333
A39: Routing assumes task success holds on the smaller model. Validate with an evaluation set before switching; a lower success rate can erase the saving through human rework.
A40: Volume scenario shows fixed platform cost spreading over more tasks, which is often the largest unit-cost lever in year one.
A41: Task success scenario: each failed task falls back to full human effort, so a lower success rate erodes value far faster than any plausible token price change.

Sheet Monthly Tracker
A1: Monthly Tracker (actuals from gateway or vendor usage exports)
A2: Enter blue columns each month at portfolio or use-case level. KPI columns calculate. Row 5 shows an example month.
A4: Month | B4: Tasks completed | C4: Successful tasks | D4: Model calls | E4: Retried calls | F4: Input tokens (M) | G4: Cached input tokens (M) | H4: Output + reasoning tokens (M) | I4: Token cost $ | J4: Platform cost $ | K4: Tokens per task (k) | L4: Cost per successful task $ | M4: Cache hit rate | N4: Retry rate | O4: Output : input ratio | P4: Calls per task
A5: 2026-01 | B5: 238000 | C5: 182000 | D5: 735000 | E5: 52000 | F5: 6650 | G5: 2900 | H5: 640 | I5: 13400 | J5: 45000 | K5: =IF(B5=0,0,(F5+H5)*1000/B5) -> 30.630252 | L5: =IF(C5=0,0,(I5+J5)/C5) -> 0.32087912 | M5: =IF(F5=0,0,G5/F5) -> 0.43609023 | N5: =IF(D5=0,0,E5/D5) -> 0.070748299 | O5: =IF(F5=0,0,H5/F5) -> 0.096240602 | P5: =IF(B5=0,0,D5/B5) -> 3.0882353
A6: 2026-02 | K6: =IF(B6=0,0,(F6+H6)*1000/B6) -> 0 | L6: =IF(C6=0,0,(I6+J6)/C6) -> 0 | M6: =IF(F6=0,0,G6/F6) -> 0 | N6: =IF(D6=0,0,E6/D6) -> 0 | O6: =IF(F6=0,0,H6/F6) -> 0 | P6: =IF(B6=0,0,D6/B6) -> 0
A7: 2026-03 | K7: =IF(B7=0,0,(F7+H7)*1000/B7) -> 0 | L7: =IF(C7=0,0,(I7+J7)/C7) -> 0 | M7: =IF(F7=0,0,G7/F7) -> 0 | N7: =IF(D7=0,0,E7/D7) -> 0 | O7: =IF(F7=0,0,H7/F7) -> 0 | P7: =IF(B7=0,0,D7/B7) -> 0
A8: 2026-04 | K8: =IF(B8=0,0,(F8+H8)*1000/B8) -> 0 | L8: =IF(C8=0,0,(I8+J8)/C8) -> 0 | M8: =IF(F8=0,0,G8/F8) -> 0 | N8: =IF(D8=0,0,E8/D8) -> 0 | O8: =IF(F8=0,0,H8/F8) -> 0 | P8: =IF(B8=0,0,D8/B8) -> 0
A9: 2026-05 | K9: =IF(B9=0,0,(F9+H9)*1000/B9) -> 0 | L9: =IF(C9=0,0,(I9+J9)/C9) -> 0 | M9: =IF(F9=0,0,G9/F9) -> 0 | N9: =IF(D9=0,0,E9/D9) -> 0 | O9: =IF(F9=0,0,H9/F9) -> 0 | P9: =IF(B9=0,0,D9/B9) -> 0
A10: 2026-06 | K10: =IF(B10=0,0,(F10+H10)*1000/B10) -> 0 | L10: =IF(C10=0,0,(I10+J10)/C10) -> 0 | M10: =IF(F10=0,0,G10/F10) -> 0 | N10: =IF(D10=0,0,E10/D10) -> 0 | O10: =IF(F10=0,0,H10/F10) -> 0 | P10: =IF(B10=0,0,D10/B10) -> 0
A11: 2026-07 | K11: =IF(B11=0,0,(F11+H11)*1000/B11) -> 0 | L11: =IF(C11=0,0,(I11+J11)/C11) -> 0 | M11: =IF(F11=0,0,G11/F11) -> 0 | N11: =IF(D11=0,0,E11/D11) -> 0 | O11: =IF(F11=0,0,H11/F11) -> 0 | P11: =IF(B11=0,0,D11/B11) -> 0
A12: 2026-08 | K12: =IF(B12=0,0,(F12+H12)*1000/B12) -> 0 | L12: =IF(C12=0,0,(I12+J12)/C12) -> 0 | M12: =IF(F12=0,0,G12/F12) -> 0 | N12: =IF(D12=0,0,E12/D12) -> 0 | O12: =IF(F12=0,0,H12/F12) -> 0 | P12: =IF(B12=0,0,D12/B12) -> 0
A13: 2026-09 | K13: =IF(B13=0,0,(F13+H13)*1000/B13) -> 0 | L13: =IF(C13=0,0,(I13+J13)/C13) -> 0 | M13: =IF(F13=0,0,G13/F13) -> 0 | N13: =IF(D13=0,0,E13/D13) -> 0 | O13: =IF(F13=0,0,H13/F13) -> 0 | P13: =IF(B13=0,0,D13/B13) -> 0
A14: 2026-10 | K14: =IF(B14=0,0,(F14+H14)*1000/B14) -> 0 | L14: =IF(C14=0,0,(I14+J14)/C14) -> 0 | M14: =IF(F14=0,0,G14/F14) -> 0 | N14: =IF(D14=0,0,E14/D14) -> 0 | O14: =IF(F14=0,0,H14/F14) -> 0 | P14: =IF(B14=0,0,D14/B14) -> 0
A15: 2026-11 | K15: =IF(B15=0,0,(F15+H15)*1000/B15) -> 0 | L15: =IF(C15=0,0,(I15+J15)/C15) -> 0 | M15: =IF(F15=0,0,G15/F15) -> 0 | N15: =IF(D15=0,0,E15/D15) -> 0 | O15: =IF(F15=0,0,H15/F15) -> 0 | P15: =IF(B15=0,0,D15/B15) -> 0
A16: 2026-12 | K16: =IF(B16=0,0,(F16+H16)*1000/B16) -> 0 | L16: =IF(C16=0,0,(I16+J16)/C16) -> 0 | M16: =IF(F16=0,0,G16/F16) -> 0 | N16: =IF(D16=0,0,E16/D16) -> 0 | O16: =IF(F16=0,0,H16/F16) -> 0 | P16: =IF(B16=0,0,D16/B16) -> 0
A18: Watch for: tokens per task creeping up (context bloat), calls per task rising (agent loops), cache hit rate falling after prompt changes, and cost per successful task rising while token price is flat (quality regression).

Sheet About
B3: GenAI Token Economics Model
B4: Version 1.0 · October 2026
B6: AI Daily | C6: One development in artificial intelligence each day, read carefully. A daily, single-topic briefing on AI for business, policy, research and society, with occasional deeper pieces like this model.
B7: Purpose | C7: Helps business and finance leaders judge whether a GenAI use case pays for itself, measured as cost per successful task rather than price per token.
B8: Author | C8: Nikhil Nan, procurement analytics and digital transformation professional. Writes AI Daily on LinkedIn.
B9: Connect | C9: linkedin.com/in/nikhil-nan
B10: Source and updates | C10: github.com/nikhilnan-git/token-economics-template
B11: License | C11: Creative Commons Attribution 4.0 International (CC BY 4.0). You may use, share and adapt this workbook, including within your organization, provided you credit the author. https://creativecommons.org/licenses/by/4.0/
B12: Suggested citation | C12: Nan, N. (2026). GenAI Token Economics Model, Version 1.0. AI Daily. github.com/nikhilnan-git/token-economics-template
B13: Feedback | C13: Suggestions and corrections are welcome via LinkedIn or a GitHub issue. Improvements will be reflected in later versions.
B14: Disclaimer | C14: The firm, use cases and figures are fictional, and the methodology is a simplified, illustrative framework rather than a validated standard. Adapt its assumptions to your own context before relying on it. Model prices reflect the general range of public list prices and are not quotes from any vendor. This workbook is not based on any organization's data, does not constitute financial advice, and reflects the author's own views.
B15: Version history | C15: 1.0 (October 2026): initial release with Start Here calculator, detailed model, sensitivity analysis and monthly KPI tracker.
